cvxpower/__init__.py
cvxpower/devices.py
cvxpower/devices_test.py
cvxpower/network.py
cvxpower/network_test.py
cvxpower-0.1.2.dist-info/DESCRIPTION.rst
cvxpower-0.1.2.dist-info/METADATA
cvxpower-0.1.2.dist-info/RECORD
cvxpower-0.1.2.dist-info/WHEEL
cvxpower-0.1.2.dist-info/metadata.json
cvxpower-0.1.2.dist-info/top_level.txt
